setup.py
jcao.egg-info/PKG-INFO
jcao.egg-info/SOURCES.txt
jcao.egg-info/dependency_links.txt
jcao.egg-info/not-zip-safe
jcao.egg-info/top_level.txt
pkg/__init__.py