Metadata-Version: 1.0
Name: jcao
Version: 0.1
Summary: This is test only
Home-page: /home/jcao/repos/personal/study/pkg
Author: jcao
Author-email: zongbo_cao@163.com
License: MIT
Platform: UNKNOWN
